qcheff/__init__.py
qcheff/iswt/__init__.py
qcheff/iswt/iswt.py
qcheff/iswt/rswt.py
qcheff/magnus/__init__.py
qcheff/magnus/magnus_time_evolution.py
qcheff/magnus/utils_gpu.py
qcheff/models/__init__.py
qcheff/models/duffing/__init__.py
qcheff/models/duffing/duffing_chain_symbolic_utils.py
qcheff/models/duffing/duffing_chain_utils.py
qcheff/models/duffing/duffing_utils.py
qcheff/models/jaynes_cummings/__init__.py
qcheff/models/jaynes_cummings/models.py
qcheff/models/jaynes_cummings/utils.py
qcheff/models/jaynes_cummings_hubbard/__init__.py
qcheff/models/jaynes_cummings_hubbard/models.py
qcheff/models/jaynes_cummings_hubbard/utils.py
qcheff/models/spin_chain/__init__.py
qcheff/models/spin_chain/utils.py
qcheff/operators/__init__.py
qcheff/operators/dense_operator.py
qcheff/operators/operator_base.py
qcheff/operators/operators.py
qcheff/operators/sparse_operator.py
qcheff/operators/utils.py
qcheff/utils/__init__.py
qcheff/utils/pulses.py
qcheff/utils/system.py
qcheff-0.2.1.dist-info/WHEEL
qcheff-0.2.1.dist-info/METADATA
qcheff-0.2.1.dist-info/RECORD
