Metadata-Version: 2.4
Name: qcheff
Version: 0.2.1
Summary: Effective Hamiltonian calculator for quantum systems.
Keywords: 
Author: abhishekchak52, taylorpatti
Author-email: abhishekchak52 <abhishekchak52@gmail.com>, taylorpatti <tpatti@nvidia.com>
License-Expression: MIT
Classifier: Programming Language :: Python
Classifier: Programming Language :: Python :: 3.11
Classifier: Programming Language :: Python :: 3.12
Classifier: Programming Language :: Python :: 3.13
Requires-Dist: more-itertools>=10.4.0
Requires-Dist: numpy>=2.0.0
Requires-Dist: scipy>=1.13
Requires-Dist: cupy-cuda11x>=13.3.0 ; extra == 'cupy-cuda11x'
Requires-Dist: cupy-cuda12x>=13.3.0 ; extra == 'cupy-cuda12x'
Requires-Dist: cupy-cuda13x>=13.6.0 ; extra == 'cupy-cuda13x'
Requires-Dist: qutip>=5.0.3.post1 ; extra == 'models'
Requires-Dist: scqubits>=4.2 ; extra == 'models'
Requires-Python: >=3.11
Provides-Extra: cupy-cuda11x
Provides-Extra: cupy-cuda12x
Provides-Extra: cupy-cuda13x
Provides-Extra: models
